{
  "usingComponents": {
    "van-button": "vant-weapp/button",
    "van-datetime-picker": "vant-weapp/datetime-picker",
    "van-action-sheet": "vant-weapp/action-sheet",
    "van-field": "vant-weapp/field",
    "van-cell": "vant-weapp/cell",
    "van-cell-group": "vant-weapp/cell-group",
    "van-toast": "vant-weapp/toast",
    "van-icon": "vant-weapp/icon",
    "van-dialog": "vant-weapp/dialog",
    "van-picker": "vant-weapp/picker",
    "van-tag": "vant-weapp/tag",
    "van-popup": "vant-weapp/popup"
  }
}